wifimangement_linux.py
wifimangement_linux-0.0.1.dist-info/LICENSE
wifimangement_linux-0.0.1.dist-info/METADATA
wifimangement_linux-0.0.1.dist-info/WHEEL
wifimangement_linux-0.0.1.dist-info/top_level.txt
wifimangement_linux-0.0.1.dist-info/RECORD
