Metadata-Version: 2.1
Name: wifimangement-linux
Version: 0.0.1
Summary: A Wi-fi Mangement tool for Linux , which is developed using Nmcli
Home-page: https://github.com/prajwalkedari/wifimangement_linux
Author: Prajwal Kedari
License: UNKNOWN
Keywords: wifi linux,wifi mangement,linux,mangement,prajwal,kedari,prajwal kedari,wifi
Platform: UNKNOWN
Classifier: Programming Language :: Python :: 3
Classifier: License :: OSI Approved :: MIT License
Classifier: Operating System :: POSIX :: Linux
Requires-Python: >=3.9
License-File: LICENSE
